ocr_genai/__init__.py
ocr_genai/ocr_package.py
ocr_genai_beta-0.1.4.dist-info/METADATA
ocr_genai_beta-0.1.4.dist-info/WHEEL
ocr_genai_beta-0.1.4.dist-info/top_level.txt
ocr_genai_beta-0.1.4.dist-info/RECORD
