Metadata-Version: 2.1
Name: ocr-genai-beta
Version: 0.1.4
Summary: A package for performing OCR and interpreting the output using OpenAI and Gemini models.
Home-page: https://github.com/Joshuaatanu/ocr_genAI/tree/main
Author: Joshua Atanu
Author-email: atanu.joshua@gmail.com
License: UNKNOWN
Platform: UNKNOWN
Classifier: Programming Language :: Python :: 3
Classifier: License :: OSI Approved :: MIT License
Classifier: Operating System :: OS Independent
Requires-Python: >=3.6
Requires-Dist: Pillow
Requires-Dist: anthropic
Requires-Dist: google-generativeai
Requires-Dist: openai
Requires-Dist: pytesseract
